restfly/__init__.py
restfly/endpoint.py
restfly/errors.py
restfly/iterator.py
restfly/session.py
restfly/utils.py
restfly/version.py
restfly-1.5.0.dist-info/LICENSE
restfly-1.5.0.dist-info/METADATA
restfly-1.5.0.dist-info/WHEEL
restfly-1.5.0.dist-info/top_level.txt
restfly-1.5.0.dist-info/RECORD
