Metadata-Version: 2.1
Name: restfly
Version: 1.5.0
Summary: REST API library framework
Author-email: Steve McGrath <smcgrath@tenable.com>
License: MIT License
Project-URL: Homepage, https://restfly.readthedocs.io
Project-URL: Repository, https://github.com/librestfly/restfly
Project-URL: Issues, https://github.com/librestfly/restfly/issues
Project-URL: Changelog, https://github.com/librestfly/restfly/blob/master/CHANGELOG.md
Keywords: rest,api,library
Classifier: Development Status :: 5 - Production/Stable
Classifier: Intended Audience :: Developers
Classifier: Topic :: Software Development
Classifier: Topic :: Software Development :: Libraries
Classifier: Topic :: Software Development :: Libraries :: Application Frameworks
Classifier: License :: OSI Approved :: MIT License
Classifier: Programming Language :: Python :: 3.7
Classifier: Programming Language :: Python :: 3.8
Classifier: Programming Language :: Python :: 3.9
Classifier: Programming Language :: Python :: 3.10
Classifier: Programming Language :: Python :: 3.11
Classifier: Programming Language :: Python :: 3.12
Requires-Python: >=3.9
License-File: LICENSE
Requires-Dist: requests>=2.32.3
Requires-Dist: python-box>=7.2.0
Requires-Dist: arrow>=1.3.0
Requires-Dist: typing-extensions>=4.12.2
